[
  {
    "updatedAt": "2026-04-14T15:25:38.123+00:00",
    "req": {
      "appCode": "YDUTE5gscDZ229CW",
      "channel": 6,
      "subChannel": 6,
      "lang": "pt-br",
      "region": "os",
      "platform": "Windows"
    },
    "rsp": {
      "payment_url": "https://topup.gryphline.com/endfield/?source_from=launcher"
    }
  },
  {
    "updatedAt": "2026-06-30T07:15:53.831+00:00",
    "req": {
      "appCode": "YDUTE5gscDZ229CW",
      "channel": 6,
      "subChannel": 6,
      "lang": "pt-br",
      "region": "os",
      "platform": "Windows"
    },
    "rsp": {
      "payment_url": "https://topup.gryphline.com/endfield/?source_from=launcher",
      "survey_url": ""
    }
  }
]
