{
  "req": {
    "appCode": "YDUTE5gscDZ229CW",
    "channel": 6,
    "subChannel": 801,
    "lang": "fr-fr",
    "region": "os",
    "platform": "Windows"
  },
  "rsp": {
    "single_ent": {
      "version_url": "https://gl-utils-public.hg-cdn.com/hg-utils/prod/eppcsuwqpaueijqk/YDUTE5gscDZ229CW/90/a1/90a14d6c554d04aa8f33e2667faf03bb.webp",
      "version_md5": "e2e6a2b52715fba1e9762953c0475438",
      "jump_url": "",
      "button_url": "",
      "button_md5": "",
      "button_hover_url": "",
      "button_hover_md5": "",
      "need_token": false
    }
  }
}
