[
  {
    "updatedAt": "2026-03-07T18:56:52.111+09:00",
    "req": {
      "appCode": "YDUTE5gscDZ229CW",
      "channel": 6,
      "subChannel": 802,
      "lang": "zh-cn",
      "region": "os",
      "platform": "Windows"
    },
    "rsp": {
      "data_version": "",
      "sidebars": [
        {
          "display_type": "DisplayType_RESERVE",
          "media": "X",
          "pic": null,
          "sidebar_labels": [],
          "grid_info": null,
          "jump_url": "https://x.com/AKEndfieldZHT",
          "need_token": false
        },
        {
          "display_type": "DisplayType_RESERVE",
          "media": "Facebook",
          "pic": null,
          "sidebar_labels": [],
          "grid_info": null,
          "jump_url": "https://www.facebook.com/ArknightsEndfieldZHT",
          "need_token": false
        },
        {
          "display_type": "DisplayType_RESERVE",
          "media": "YouTube",
          "pic": null,
          "sidebar_labels": [],
          "grid_info": null,
          "jump_url": "https://www.youtube.com/@arknightsendfieldCHT",
          "need_token": false
        },
        {
          "display_type": "DisplayType_RESERVE",
          "media": "Discord",
          "pic": null,
          "sidebar_labels": [],
          "grid_info": null,
          "jump_url": "https://discord.com/invite/akendfield",
          "need_token": false
        },
        {
          "display_type": "DisplayType_RESERVE",
          "media": "Skland_gl",
          "pic": {
            "url": "https://gl-utils-public.hg-cdn.com/hg-utils/prod/eppcsuwqpaueijqk/YDUTE5gscDZ229CW/b6/70/b67039098ae6c66d91172b80d516a2f4.png",
            "md5": "b50505ca1ec2e22928aea67ff70e4d7c",
            "description": "扫码下载SKPORT APP"
          },
          "sidebar_labels": [
            {
              "content": "每日签到",
              "jump_url": "https://game.skport.com/endfield/sign-in?header=0&hg_media=launcher&hg_link_campaign=icon",
              "need_token": false
            },
            {
              "content": "地图工具",
              "jump_url": "https://game.skport.com/map/endfield?header=0&ctr_orientation=landscape&hg_media=launcher&hg_link_campaign=icon",
              "need_token": false
            },
            {
              "content": "养成建议",
              "jump_url": "https://game.skport.com/tools/endfield/list?header=0&ctr_orientation=landscape&routeId=1&hg_media=launcher&hg_link_campaign=icon",
              "need_token": false
            },
            {
              "content": "前往SKPORT",
              "jump_url": "https://www.skport.com/?hg_source=official&hg_media=launcher",
              "need_token": false
            }
          ],
          "grid_info": null,
          "jump_url": "https://www.skport.com/?hg_source=official&hg_media=launcher",
          "need_token": true
        },
        {
          "display_type": "DisplayType_RESERVE",
          "media": "CS_gl",
          "pic": null,
          "sidebar_labels": [],
          "grid_info": null,
          "jump_url": "https://gryphline.helpshift.com/hc/zh/4-arknights-endfield/",
          "need_token": true
        }
      ]
    }
  },
  {
    "updatedAt": "2026-05-14T03:35:52.618+00:00",
    "req": {
      "appCode": "YDUTE5gscDZ229CW",
      "channel": 6,
      "subChannel": 802,
      "lang": "zh-cn",
      "region": "os",
      "platform": "Windows"
    },
    "rsp": {
      "data_version": "",
      "sidebars": [
        {
          "display_type": "DisplayType_RESERVE",
          "media": "X",
          "pic": null,
          "sidebar_labels": [],
          "grid_info": null,
          "jump_url": "https://x.com/AKEndfieldZHT",
          "need_token": false
        },
        {
          "display_type": "DisplayType_RESERVE",
          "media": "Facebook",
          "pic": null,
          "sidebar_labels": [],
          "grid_info": null,
          "jump_url": "https://www.facebook.com/ArknightsEndfieldZHT",
          "need_token": false
        },
        {
          "display_type": "DisplayType_RESERVE",
          "media": "YouTube",
          "pic": null,
          "sidebar_labels": [],
          "grid_info": null,
          "jump_url": "https://www.youtube.com/@arknightsendfieldCHT",
          "need_token": false
        },
        {
          "display_type": "DisplayType_RESERVE",
          "media": "Discord",
          "pic": null,
          "sidebar_labels": [],
          "grid_info": null,
          "jump_url": "https://discord.com/invite/akendfield",
          "need_token": false
        },
        {
          "display_type": "DisplayType_RESERVE",
          "media": "Skland_gl",
          "pic": {
            "url": "https://gl-utils-public.hg-cdn.com/hg-utils/prod/eppcsuwqpaueijqk/YDUTE5gscDZ229CW/b6/70/b67039098ae6c66d91172b80d516a2f4.png",
            "md5": "b50505ca1ec2e22928aea67ff70e4d7c",
            "description": "扫码下载SKPORT APP"
          },
          "sidebar_labels": [
            {
              "content": "每日签到",
              "jump_url": "https://game.skport.com/endfield/sign-in?header=0&hg_media=launcher&hg_link_campaign=icon",
              "need_token": false
            },
            {
              "content": "地图工具",
              "jump_url": "https://game.skport.com/map/endfield?header=0&hg_media=launcher&hg_link_campaign=icon",
              "need_token": false
            },
            {
              "content": "养成建议",
              "jump_url": "https://game.skport.com/tools/endfield/list?header=0&ctr_orientation=landscape&routeId=1&hg_media=launcher&hg_link_campaign=icon",
              "need_token": false
            },
            {
              "content": "前往SKPORT",
              "jump_url": "https://www.skport.com/?hg_source=official&hg_media=launcher",
              "need_token": false
            }
          ],
          "grid_info": null,
          "jump_url": "https://www.skport.com/?hg_source=official&hg_media=launcher",
          "need_token": true
        },
        {
          "display_type": "DisplayType_RESERVE",
          "media": "CS_gl",
          "pic": null,
          "sidebar_labels": [],
          "grid_info": null,
          "jump_url": "https://gryphline.helpshift.com/hc/zh/4-arknights-endfield/",
          "need_token": true
        }
      ]
    }
  },
  {
    "updatedAt": "2026-06-25T09:01:08.456+00:00",
    "req": {
      "appCode": "YDUTE5gscDZ229CW",
      "channel": 6,
      "subChannel": 802,
      "lang": "zh-cn",
      "region": "os",
      "platform": "Windows"
    },
    "rsp": {
      "data_version": "",
      "sidebars": [
        {
          "display_type": "DisplayType_DEFAULT",
          "media": "X",
          "pic": null,
          "sidebar_labels": [],
          "grid_info": null,
          "jump_url": "https://x.com/AKEndfieldZHT",
          "need_token": false
        },
        {
          "display_type": "DisplayType_DEFAULT",
          "media": "Facebook",
          "pic": null,
          "sidebar_labels": [],
          "grid_info": null,
          "jump_url": "https://www.facebook.com/ArknightsEndfieldZHT",
          "need_token": false
        },
        {
          "display_type": "DisplayType_DEFAULT",
          "media": "YouTube",
          "pic": null,
          "sidebar_labels": [],
          "grid_info": null,
          "jump_url": "https://www.youtube.com/@arknightsendfieldCHT",
          "need_token": false
        },
        {
          "display_type": "DisplayType_DEFAULT",
          "media": "Discord",
          "pic": null,
          "sidebar_labels": [],
          "grid_info": null,
          "jump_url": "https://discord.com/invite/akendfield",
          "need_token": false
        },
        {
          "display_type": "DisplayType_LIST",
          "media": "Skland_gl",
          "pic": {
            "url": "https://gl-utils-public.hg-cdn.com/hg-utils/prod/eppcsuwqpaueijqk/YDUTE5gscDZ229CW/b6/70/b67039098ae6c66d91172b80d516a2f4.png",
            "md5": "b50505ca1ec2e22928aea67ff70e4d7c",
            "description": "扫码下载SKPORT APP"
          },
          "sidebar_labels": [
            {
              "content": "每日签到",
              "jump_url": "https://game.skport.com/endfield/sign-in?header=0&hg_media=launcher&hg_link_campaign=icon",
              "need_token": false,
              "pic_url": ""
            },
            {
              "content": "地图工具",
              "jump_url": "https://game.skport.com/map/endfield?header=0&hg_media=launcher&hg_link_campaign=icon",
              "need_token": false,
              "pic_url": ""
            },
            {
              "content": "养成建议",
              "jump_url": "https://game.skport.com/tools/endfield/list?header=0&ctr_orientation=landscape&routeId=1&hg_media=launcher&hg_link_campaign=icon",
              "need_token": false,
              "pic_url": ""
            },
            {
              "content": "前往SKPORT",
              "jump_url": "https://www.skport.com/?hg_source=official&hg_media=launcher",
              "need_token": false,
              "pic_url": ""
            }
          ],
          "grid_info": null,
          "jump_url": "https://www.skport.com/?hg_source=official&hg_media=launcher",
          "need_token": true
        },
        {
          "display_type": "DisplayType_DEFAULT",
          "media": "CS_gl",
          "pic": null,
          "sidebar_labels": [],
          "grid_info": null,
          "jump_url": "https://gryphline.helpshift.com/hc/zh/4-arknights-endfield/",
          "need_token": true
        }
      ]
    }
  },
  {
    "updatedAt": "2026-06-25T10:31:06.574+00:00",
    "req": {
      "appCode": "YDUTE5gscDZ229CW",
      "channel": 6,
      "subChannel": 802,
      "lang": "zh-cn",
      "region": "os",
      "platform": "Windows"
    },
    "rsp": {
      "data_version": "",
      "sidebars": [
        {
          "display_type": "DisplayType_RESERVE",
          "media": "X",
          "pic": null,
          "sidebar_labels": [],
          "grid_info": null,
          "jump_url": "https://x.com/AKEndfieldZHT",
          "need_token": false
        },
        {
          "display_type": "DisplayType_RESERVE",
          "media": "Facebook",
          "pic": null,
          "sidebar_labels": [],
          "grid_info": null,
          "jump_url": "https://www.facebook.com/ArknightsEndfieldZHT",
          "need_token": false
        },
        {
          "display_type": "DisplayType_RESERVE",
          "media": "YouTube",
          "pic": null,
          "sidebar_labels": [],
          "grid_info": null,
          "jump_url": "https://www.youtube.com/@arknightsendfieldCHT",
          "need_token": false
        },
        {
          "display_type": "DisplayType_RESERVE",
          "media": "Discord",
          "pic": null,
          "sidebar_labels": [],
          "grid_info": null,
          "jump_url": "https://discord.com/invite/akendfield",
          "need_token": false
        },
        {
          "display_type": "DisplayType_RESERVE",
          "media": "Skland_gl",
          "pic": {
            "url": "https://gl-utils-public.hg-cdn.com/hg-utils/prod/eppcsuwqpaueijqk/YDUTE5gscDZ229CW/b6/70/b67039098ae6c66d91172b80d516a2f4.png",
            "md5": "b50505ca1ec2e22928aea67ff70e4d7c",
            "description": "扫码下载SKPORT APP"
          },
          "sidebar_labels": [
            {
              "content": "每日签到",
              "jump_url": "https://game.skport.com/endfield/sign-in?header=0&hg_media=launcher&hg_link_campaign=icon",
              "need_token": false,
              "pic_url": ""
            },
            {
              "content": "地图工具",
              "jump_url": "https://game.skport.com/map/endfield?header=0&hg_media=launcher&hg_link_campaign=icon",
              "need_token": false,
              "pic_url": ""
            },
            {
              "content": "养成建议",
              "jump_url": "https://game.skport.com/tools/endfield/list?header=0&ctr_orientation=landscape&routeId=1&hg_media=launcher&hg_link_campaign=icon",
              "need_token": false,
              "pic_url": ""
            },
            {
              "content": "前往SKPORT",
              "jump_url": "https://www.skport.com/?hg_source=official&hg_media=launcher",
              "need_token": false,
              "pic_url": ""
            }
          ],
          "grid_info": null,
          "jump_url": "https://www.skport.com/?hg_source=official&hg_media=launcher",
          "need_token": true
        },
        {
          "display_type": "DisplayType_RESERVE",
          "media": "CS_gl",
          "pic": null,
          "sidebar_labels": [],
          "grid_info": null,
          "jump_url": "https://gryphline.helpshift.com/hc/zh/4-arknights-endfield/",
          "need_token": true
        }
      ]
    }
  },
  {
    "updatedAt": "2026-07-13T07:51:17.956+00:00",
    "req": {
      "appCode": "YDUTE5gscDZ229CW",
      "channel": 6,
      "subChannel": 802,
      "lang": "zh-cn",
      "region": "os",
      "platform": "Windows"
    },
    "rsp": {
      "data_version": "",
      "sidebars": [
        {
          "display_type": "DisplayType_DEFAULT",
          "media": "X",
          "pic": null,
          "sidebar_labels": [],
          "grid_info": null,
          "jump_url": "https://x.com/AKEndfieldZHT",
          "need_token": false
        },
        {
          "display_type": "DisplayType_DEFAULT",
          "media": "Facebook",
          "pic": null,
          "sidebar_labels": [],
          "grid_info": null,
          "jump_url": "https://www.facebook.com/ArknightsEndfieldZHT",
          "need_token": false
        },
        {
          "display_type": "DisplayType_DEFAULT",
          "media": "YouTube",
          "pic": null,
          "sidebar_labels": [],
          "grid_info": null,
          "jump_url": "https://www.youtube.com/@arknightsendfieldCHT",
          "need_token": false
        },
        {
          "display_type": "DisplayType_DEFAULT",
          "media": "Discord",
          "pic": null,
          "sidebar_labels": [],
          "grid_info": null,
          "jump_url": "https://discord.com/invite/akendfield",
          "need_token": false
        },
        {
          "display_type": "DisplayType_LIST",
          "media": "Skland_gl",
          "pic": {
            "url": "https://gl-utils-public.hg-cdn.com/hg-utils/prod/eppcsuwqpaueijqk/YDUTE5gscDZ229CW/b6/70/b67039098ae6c66d91172b80d516a2f4.png",
            "md5": "b50505ca1ec2e22928aea67ff70e4d7c",
            "description": "扫码下载SKPORT APP"
          },
          "sidebar_labels": [
            {
              "content": "每日签到",
              "jump_url": "https://game.skport.com/endfield/sign-in?header=0&hg_media=launcher&hg_link_campaign=icon",
              "need_token": false,
              "pic_url": ""
            },
            {
              "content": "前往SKPORT",
              "jump_url": "https://www.skport.com/?hg_source=official&hg_media=launcher",
              "need_token": false,
              "pic_url": ""
            }
          ],
          "grid_info": null,
          "jump_url": "https://www.skport.com/?hg_source=official&hg_media=launcher",
          "need_token": true
        },
        {
          "display_type": "DisplayType_DEFAULT",
          "media": "CS_gl",
          "pic": null,
          "sidebar_labels": [],
          "grid_info": null,
          "jump_url": "https://gryphline.helpshift.com/hc/zh/4-arknights-endfield/",
          "need_token": true
        }
      ]
    }
  },
  {
    "updatedAt": "2026-07-13T08:16:02.197+00:00",
    "req": {
      "appCode": "YDUTE5gscDZ229CW",
      "channel": 6,
      "subChannel": 802,
      "lang": "zh-cn",
      "region": "os",
      "platform": "Windows"
    },
    "rsp": {
      "data_version": "",
      "sidebars": [
        {
          "display_type": "DisplayType_DEFAULT",
          "media": "X",
          "pic": null,
          "sidebar_labels": [],
          "grid_info": null,
          "jump_url": "https://x.com/AKEndfieldZHT",
          "need_token": false
        },
        {
          "display_type": "DisplayType_DEFAULT",
          "media": "Facebook",
          "pic": null,
          "sidebar_labels": [],
          "grid_info": null,
          "jump_url": "https://www.facebook.com/ArknightsEndfieldZHT",
          "need_token": false
        },
        {
          "display_type": "DisplayType_DEFAULT",
          "media": "YouTube",
          "pic": null,
          "sidebar_labels": [],
          "grid_info": null,
          "jump_url": "https://www.youtube.com/@arknightsendfieldCHT",
          "need_token": false
        },
        {
          "display_type": "DisplayType_DEFAULT",
          "media": "Discord",
          "pic": null,
          "sidebar_labels": [],
          "grid_info": null,
          "jump_url": "https://discord.com/invite/akendfield",
          "need_token": false
        },
        {
          "display_type": "DisplayType_LIST",
          "media": "Skland_gl",
          "pic": {
            "url": "https://gl-utils-public.hg-cdn.com/hg-utils/prod/eppcsuwqpaueijqk/YDUTE5gscDZ229CW/b6/70/b67039098ae6c66d91172b80d516a2f4.png",
            "md5": "b50505ca1ec2e22928aea67ff70e4d7c",
            "description": "扫码下载SKPORT APP"
          },
          "sidebar_labels": [
            {
              "content": "每日签到",
              "jump_url": "https://game.skport.com/endfield/sign-in?header=0&hg_media=launcher&hg_link_campaign=icon",
              "need_token": false,
              "pic_url": ""
            },
            {
              "content": "前往SKPORT",
              "jump_url": "https://www.skport.com/?hg_source=official&hg_media=launcher",
              "need_token": false,
              "pic_url": ""
            }
          ],
          "grid_info": null,
          "jump_url": "https://www.skport.com/?hg_source=official&hg_media=launcher",
          "need_token": true
        },
        {
          "display_type": "DisplayType_DEFAULT",
          "media": "CS_gl",
          "pic": null,
          "sidebar_labels": [],
          "grid_info": null,
          "jump_url": "https://gryphline.helpshift.com/hc/zh/4-arknights-endfield/",
          "need_token": true
        },
        {
          "display_type": "DisplayType_GRID",
          "media": "SklandTool",
          "pic": null,
          "sidebar_labels": [
            {
              "content": "每日签到",
              "jump_url": "https://game.skport.com/endfield/sign-in?header=0&hg_media=launcher&hg_link_campaign=ninesquare&hg_link_name=signin",
              "need_token": true,
              "pic_url": "https://gl-utils-public.hg-cdn.com/hg-utils/prod/eppcsuwqpaueijqk/YDUTE5gscDZ229CW/2e/34/2e3436c6cfdfcc43a8a22d890db4d828.png"
            },
            {
              "content": "协议终端",
              "jump_url": "https://game.skport.com/endfield/game-data?header=0&hg_media=launcher&hg_link_campaign=ninesquare&hg_link_name=ProtocolTerminal",
              "need_token": true,
              "pic_url": "https://gl-utils-public.hg-cdn.com/hg-utils/prod/eppcsuwqpaueijqk/YDUTE5gscDZ229CW/42/d9/42d9b3ed1ebb18983ab19469e307508f.png"
            },
            {
              "content": "养成建议",
              "jump_url": "https://game.skport.com/tools/endfield/list?header=0&ctr_orientation=landscape&routeId=1&hg_media=launcher&hg_link_campaign=ninesquare&hg_link_name=buildguide",
              "need_token": true,
              "pic_url": "https://gl-utils-public.hg-cdn.com/hg-utils/prod/eppcsuwqpaueijqk/YDUTE5gscDZ229CW/e6/a9/e6a9aec5edf8bead8dbdef8a8effed95.png"
            },
            {
              "content": "配队推荐",
              "jump_url": "https://game.skport.com/tools/endfield/list?header=0&ctr_orientation=landscape&routeId=0&hg_media=launcher&hg_link_campaign=ninesquare&hg_link_name=teampick",
              "need_token": true,
              "pic_url": "https://gl-utils-public.hg-cdn.com/hg-utils/prod/eppcsuwqpaueijqk/YDUTE5gscDZ229CW/99/d7/99d7bc23e2e03b0ce162f4c089aa605e.png"
            },
            {
              "content": "地图工具",
              "jump_url": "https://game.skport.com/map/endfield?header=0&ctr_orientation=landscape&hg_media=launcher&hg_link_campaign=ninesquare&hg_link_name=maptool",
              "need_token": true,
              "pic_url": "https://gl-utils-public.hg-cdn.com/hg-utils/prod/eppcsuwqpaueijqk/YDUTE5gscDZ229CW/5a/23/5a2365bee3f99debb41df64f67f9e0ea.png"
            },
            {
              "content": "WIKI",
              "jump_url": "https://wiki.skport.com/endfield?/hg_media=launcher&hg_link_campaign=ninesquare&hg_link_name=wiki",
              "need_token": false,
              "pic_url": "https://gl-utils-public.hg-cdn.com/hg-utils/prod/eppcsuwqpaueijqk/YDUTE5gscDZ229CW/24/f3/24f3fbad6e266fc80b04e73444e26b2a.png"
            }
          ],
          "grid_info": null,
          "jump_url": "",
          "need_token": true
        }
      ]
    }
  },
  {
    "updatedAt": "2026-07-13T09:01:31.042+00:00",
    "req": {
      "appCode": "YDUTE5gscDZ229CW",
      "channel": 6,
      "subChannel": 802,
      "lang": "zh-cn",
      "region": "os",
      "platform": "Windows"
    },
    "rsp": {
      "data_version": "",
      "sidebars": [
        {
          "display_type": "DisplayType_DEFAULT",
          "media": "X",
          "pic": null,
          "sidebar_labels": [],
          "grid_info": null,
          "jump_url": "https://x.com/AKEndfieldZHT",
          "need_token": false
        },
        {
          "display_type": "DisplayType_DEFAULT",
          "media": "Facebook",
          "pic": null,
          "sidebar_labels": [],
          "grid_info": null,
          "jump_url": "https://www.facebook.com/ArknightsEndfieldZHT",
          "need_token": false
        },
        {
          "display_type": "DisplayType_DEFAULT",
          "media": "YouTube",
          "pic": null,
          "sidebar_labels": [],
          "grid_info": null,
          "jump_url": "https://www.youtube.com/@arknightsendfieldCHT",
          "need_token": false
        },
        {
          "display_type": "DisplayType_DEFAULT",
          "media": "Discord",
          "pic": null,
          "sidebar_labels": [],
          "grid_info": null,
          "jump_url": "https://discord.com/invite/akendfield",
          "need_token": false
        },
        {
          "display_type": "DisplayType_LIST",
          "media": "Skland_gl",
          "pic": {
            "url": "https://gl-utils-public.hg-cdn.com/hg-utils/prod/eppcsuwqpaueijqk/YDUTE5gscDZ229CW/b6/70/b67039098ae6c66d91172b80d516a2f4.png",
            "md5": "b50505ca1ec2e22928aea67ff70e4d7c",
            "description": "扫码下载SKPORT APP"
          },
          "sidebar_labels": [
            {
              "content": "每日签到",
              "jump_url": "https://game.skport.com/endfield/sign-in?header=0&hg_media=launcher&hg_link_campaign=icon",
              "need_token": false,
              "pic_url": ""
            },
            {
              "content": "前往SKPORT",
              "jump_url": "https://www.skport.com/?hg_source=official&hg_media=launcher",
              "need_token": false,
              "pic_url": ""
            }
          ],
          "grid_info": null,
          "jump_url": "https://www.skport.com/?hg_source=official&hg_media=launcher",
          "need_token": true
        },
        {
          "display_type": "DisplayType_DEFAULT",
          "media": "CS_gl",
          "pic": null,
          "sidebar_labels": [],
          "grid_info": null,
          "jump_url": "https://gryphline.helpshift.com/hc/zh/4-arknights-endfield/",
          "need_token": true
        },
        {
          "display_type": "DisplayType_GRID",
          "media": "SklandTool",
          "pic": null,
          "sidebar_labels": [
            {
              "content": "每日签到",
              "jump_url": "https://game.skport.com/endfield/sign-in?header=0&hg_media=launcher&hg_link_campaign=ninesquare&hg_link_name=signin",
              "need_token": true,
              "pic_url": "https://gl-utils-public.hg-cdn.com/hg-utils/prod/eppcsuwqpaueijqk/YDUTE5gscDZ229CW/36/de/36de343e2e73b9ff117664bf687f605d.png"
            },
            {
              "content": "协议终端",
              "jump_url": "https://game.skport.com/endfield/game-data?header=0&hg_media=launcher&hg_link_campaign=ninesquare&hg_link_name=ProtocolTerminal",
              "need_token": true,
              "pic_url": "https://gl-utils-public.hg-cdn.com/hg-utils/prod/eppcsuwqpaueijqk/YDUTE5gscDZ229CW/70/db/70db32e12d842da5c5cbb156f1a5412f.png"
            },
            {
              "content": "养成建议",
              "jump_url": "https://game.skport.com/tools/endfield/list?header=0&ctr_orientation=landscape&routeId=1&hg_media=launcher&hg_link_campaign=ninesquare&hg_link_name=buildguide",
              "need_token": true,
              "pic_url": "https://gl-utils-public.hg-cdn.com/hg-utils/prod/eppcsuwqpaueijqk/YDUTE5gscDZ229CW/47/c5/47c588f6c73fa8d27313d0ce2fd4438d.png"
            },
            {
              "content": "配队推荐",
              "jump_url": "https://game.skport.com/tools/endfield/list?header=0&ctr_orientation=landscape&routeId=0&hg_media=launcher&hg_link_campaign=ninesquare&hg_link_name=teampick",
              "need_token": true,
              "pic_url": "https://gl-utils-public.hg-cdn.com/hg-utils/prod/eppcsuwqpaueijqk/YDUTE5gscDZ229CW/37/21/37214575a40a8130bf755b4b43b1ee36.png"
            },
            {
              "content": "地图工具",
              "jump_url": "https://game.skport.com/map/endfield?header=0&ctr_orientation=landscape&hg_media=launcher&hg_link_campaign=ninesquare&hg_link_name=maptool",
              "need_token": true,
              "pic_url": "https://gl-utils-public.hg-cdn.com/hg-utils/prod/eppcsuwqpaueijqk/YDUTE5gscDZ229CW/c1/b8/c1b8f91b3f49dbcaf3c59572663c027e.png"
            },
            {
              "content": "WIKI",
              "jump_url": "https://wiki.skport.com/endfield?/hg_media=launcher&hg_link_campaign=ninesquare&hg_link_name=wiki",
              "need_token": false,
              "pic_url": "https://gl-utils-public.hg-cdn.com/hg-utils/prod/eppcsuwqpaueijqk/YDUTE5gscDZ229CW/99/36/99369f7458c91cc4f36b79cb0494bf8b.png"
            }
          ],
          "grid_info": null,
          "jump_url": "",
          "need_token": true
        }
      ]
    }
  },
  {
    "updatedAt": "2026-07-13T12:21:22.430+00:00",
    "req": {
      "appCode": "YDUTE5gscDZ229CW",
      "channel": 6,
      "subChannel": 802,
      "lang": "zh-cn",
      "region": "os",
      "platform": "Windows"
    },
    "rsp": {
      "data_version": "",
      "sidebars": [
        {
          "display_type": "DisplayType_DEFAULT",
          "media": "X",
          "pic": null,
          "sidebar_labels": [],
          "grid_info": null,
          "jump_url": "https://x.com/AKEndfieldZHT",
          "need_token": false
        },
        {
          "display_type": "DisplayType_DEFAULT",
          "media": "Facebook",
          "pic": null,
          "sidebar_labels": [],
          "grid_info": null,
          "jump_url": "https://www.facebook.com/ArknightsEndfieldZHT",
          "need_token": false
        },
        {
          "display_type": "DisplayType_DEFAULT",
          "media": "YouTube",
          "pic": null,
          "sidebar_labels": [],
          "grid_info": null,
          "jump_url": "https://www.youtube.com/@arknightsendfieldCHT",
          "need_token": false
        },
        {
          "display_type": "DisplayType_DEFAULT",
          "media": "Discord",
          "pic": null,
          "sidebar_labels": [],
          "grid_info": null,
          "jump_url": "https://discord.com/invite/akendfield",
          "need_token": false
        },
        {
          "display_type": "DisplayType_LIST",
          "media": "Skland_gl",
          "pic": {
            "url": "https://gl-utils-public.hg-cdn.com/hg-utils/prod/eppcsuwqpaueijqk/YDUTE5gscDZ229CW/b6/70/b67039098ae6c66d91172b80d516a2f4.png",
            "md5": "b50505ca1ec2e22928aea67ff70e4d7c",
            "description": "扫码下载SKPORT APP"
          },
          "sidebar_labels": [
            {
              "content": "每日签到",
              "jump_url": "https://game.skport.com/endfield/sign-in?header=0&hg_media=launcher&hg_link_campaign=icon",
              "need_token": false,
              "pic_url": ""
            },
            {
              "content": "前往SKPORT",
              "jump_url": "https://www.skport.com/?hg_source=official&hg_media=launcher",
              "need_token": false,
              "pic_url": ""
            }
          ],
          "grid_info": null,
          "jump_url": "https://www.skport.com/?hg_source=official&hg_media=launcher",
          "need_token": true
        },
        {
          "display_type": "DisplayType_DEFAULT",
          "media": "CS_gl",
          "pic": null,
          "sidebar_labels": [],
          "grid_info": null,
          "jump_url": "https://gryphline.helpshift.com/hc/zh/4-arknights-endfield/",
          "need_token": true
        },
        {
          "display_type": "DisplayType_GRID",
          "media": "SklandTool",
          "pic": null,
          "sidebar_labels": [
            {
              "content": "每日签到",
              "jump_url": "https://game.skport.com/endfield/sign-in?header=0&hg_media=launcher&hg_link_campaign=ninesquare&hg_link_name=signin",
              "need_token": true,
              "pic_url": "https://gl-utils-public.hg-cdn.com/hg-utils/prod/eppcsuwqpaueijqk/YDUTE5gscDZ229CW/36/de/36de343e2e73b9ff117664bf687f605d.png"
            },
            {
              "content": "协议终端",
              "jump_url": "https://game.skport.com/endfield/game-data?header=0&hg_media=launcher&hg_link_campaign=ninesquare&hg_link_name=ProtocolTerminal",
              "need_token": true,
              "pic_url": "https://gl-utils-public.hg-cdn.com/hg-utils/prod/eppcsuwqpaueijqk/YDUTE5gscDZ229CW/70/db/70db32e12d842da5c5cbb156f1a5412f.png"
            },
            {
              "content": "配队推荐",
              "jump_url": "https://game.skport.com/tools/endfield/list?header=0&ctr_orientation=landscape&routeId=0&hg_media=launcher&hg_link_campaign=ninesquare&hg_link_name=teampick",
              "need_token": true,
              "pic_url": "https://gl-utils-public.hg-cdn.com/hg-utils/prod/eppcsuwqpaueijqk/YDUTE5gscDZ229CW/37/21/37214575a40a8130bf755b4b43b1ee36.png"
            },
            {
              "content": "地图工具",
              "jump_url": "https://game.skport.com/map/endfield?header=0&ctr_orientation=landscape&hg_media=launcher&hg_link_campaign=ninesquare&hg_link_name=maptool",
              "need_token": true,
              "pic_url": "https://gl-utils-public.hg-cdn.com/hg-utils/prod/eppcsuwqpaueijqk/YDUTE5gscDZ229CW/c1/b8/c1b8f91b3f49dbcaf3c59572663c027e.png"
            },
            {
              "content": "WIKI",
              "jump_url": "https://wiki.skport.com/endfield?/hg_media=launcher&hg_link_campaign=ninesquare&hg_link_name=wiki",
              "need_token": false,
              "pic_url": "https://gl-utils-public.hg-cdn.com/hg-utils/prod/eppcsuwqpaueijqk/YDUTE5gscDZ229CW/99/36/99369f7458c91cc4f36b79cb0494bf8b.png"
            },
            {
              "content": "养成建议",
              "jump_url": "https://game.skport.com/tools/endfield/list?header=0&ctr_orientation=landscape&routeId=1&hg_media=launcher&hg_link_campaign=ninesquare&hg_link_name=buildguide",
              "need_token": true,
              "pic_url": "https://gl-utils-public.hg-cdn.com/hg-utils/prod/eppcsuwqpaueijqk/YDUTE5gscDZ229CW/47/c5/47c588f6c73fa8d27313d0ce2fd4438d.png"
            }
          ],
          "grid_info": null,
          "jump_url": "",
          "need_token": true
        }
      ]
    }
  }
]
